{
  "nhanvien": [
    {
      "name": "Son doe...",
      "address": "asdas",
      "email": "asdads",
      "bday": "2022-05-12",
      "phone": "asdadsads",
      "password": "password",
      "radio": "male",
      "id": 11
    },
    {
      "name": "Son doe...",
      "address": "dasdsas",
      "email": "asdasds",
      "bday": "",
      "phone": "asdasda",
      "password": "password",
      "radio": "male",
      "id": 12
    }
  ],
  "comments": [
    {
      "id": 1,
      "body": "some comment",
      "postId": 1
    }
  ],
  "profile": {
    "name": "typicode"
  }
}